{"hiddenService":"fzerooofqztxdkyy.onion","webDetected":true,"sshDetected":false,"ricochetDetected":false,"ircDetected":false,"ftpDetected":false,"smtpDetected":false,"bitcoinDetected":false,"mongodbDetected":false,"vncDetected":false,"xmppDetected":false,"serverPoweredBy":"","serverVersion":"Apache/2.4.10 (Debian) OpenSSL/1.0.1t","foundApacheModStatus":true,"relatedOnionServices":null,"relatedOnionDomains":["il.f00.net"],"linkedSites":["www.torproject.org"],"internalPages":["","fzerooofqztxdkyy.onion"],"ipAddresses":["51.255.204.60"],"openDirectories":null,"exifImages":null,"interestingFiles":null,"pageReferencedDirectories":["/cgi-bin","fzerooofqztxdkyy.onion"],"pgpKeys":null,"hashes":["108689daed8888ee33ba608a85337160524b0a59"],"snapshot":"\u003chtml\u003e\n\u003chead\u003e\n\u003ctitle\u003evmail\u003c/title\u003e\n\u003c/head\u003e\n\u003cbody\u003e\n\u003cb\u003eWelcome to vmail.\u003c/b\u003e\u003cbr /\u003e\n\u003cul\u003e\n\u003cli/\u003e\u003ca href=\"/cgi-bin/greylist_suspend\"\u003eSuspend Greylisting\u003c/a\u003e\n\u003cli/\u003e\u003ca href=\"/squirrelmail\"\u003eWebmail\u003c/a\u003e\n\u003cli/\u003eTor(\u003ca href=\"https://www.torproject.org\"\u003e?\u003c/a\u003e) hidden service: \u003ca href=\"http://fzerooofqztxdkyy.onion/\"\u003efzerooofqztxdkyy.onion\u003c/a\u003e\n\u003c/ul\u003e\n\u003c/body\u003e\n\u003c/html\u003e\n","pageTitle":"vmail","responseHeaders":{"ACCEPT-RANGES":"bytes","CONTENT-TYPE":"text/html","DATE":"Tue, 26 Jul 2016 04:54:50 GMT","ETAG":"\"15f-52eabc1805660-gzip\"","LAST-MODIFIED":"Tue, 22 Mar 2016 23:41:44 GMT","SERVER":"Apache/2.4.10 (Debian)","STRICT-TRANSPORT-SECURITY":"max-age=31536000; includeSubDomains","VARY":"Accept-Encoding"},"bitcoinAddresses":null,"sshKey":"","ftpFingerprint":"","ftpBanner":"","smtpFingerprint":"","smtpBanner":""}
