{"hiddenService":"qbj5eznyjs5q7rok.onion","webDetected":true,"sshDetected":true,"ricochetDetected":false,"ircDetected":false,"ftpDetected":false,"smtpDetected":false,"bitcoinDetected":false,"mongodbDetected":false,"vncDetected":false,"xmppDetected":false,"serverPoweredBy":"","serverVersion":"Apache","foundApacheModStatus":false,"relatedOnionServices":null,"relatedOnionDomains":null,"linkedSites":["www.preev.com","www.bitboat.net","www.w3.org"],"internalPages":[""],"ipAddresses":null,"openDirectories":null,"exifImages":null,"interestingFiles":null,"pageReferencedDirectories":["corps","corps/images"],"pgpKeys":null,"hashes":["146d8f60ba2f170140c1dd427d8486972f3eaf7a"],"snapshot":"Connection error: SQLSTATE[HY000] [2002] Can't connect to local MySQL server through socket '/var/run/mysqld/mysqld.sock' (2 \"No such file or directory\")\u003c!DOCTYPE html PUBLIC \"-//W3C//DTD XHTML 1.0 Strict//EN\" \"http://www.w3.org/TR/xhtml1/DTD/xhtml1-strict.dtd\"\u003e\r\n\u003chtml xmlns=\"http://www.w3.org/1999/xhtml\" xml:lang=\"en\" lang=\"en\"\u003e\r\n\r\n\u003chead\u003e\r\n\t\u003ctitle\u003eDevilFunding // The crowdfunding of the darkweb\u003c/title\u003e\r\n\t\u003cmeta http-equiv=\"Content-Type\" content=\"text/html; charset=utf-8\" /\u003e\r\n\t\u003cmeta name=\"description\" content=\"Crowdfunding\" /\u003e\r\n\t\u003clink rel=\"stylesheet\" type=\"text/css\" href=\"corps/style.css\" media=\"screen\" /\u003e\r\n\t\r\n\u003c/head\u003e\r\n\r\n\u003cbody\u003e\r\n    \t\r\n\t\u003cdiv id=\"site\"\u003e\r\n\t\u003cdiv id=\"header\"\u003e\r\n\r\n\u003c!-- head--\u003e\r\n\r\n\u003c!-- [DEBUT] BARRE INFOS --\u003e\r\n        \u003c!-- Information bar --\u003e\r\n    \t\u003cdiv id=\"barre-infos\"\u003e\r\n\t\t\u003c!-- user is connect  welcome barre--\u003e\r\n\t\tConnection error: SQLSTATE[HY000] [2002] Can't connect to local MySQL server through socket '/var/run/mysqld/mysqld.sock' (2 \"No such file or directory\")\u003c!-- user isn't connect  visitor barre--\u003e\r\n\t\t\u003cp\u003eWelcome Visitor !\u0026nbsp;\u0026nbsp;\u0026nbsp;\u0026nbsp;\u0026nbsp;\u0026nbsp;\u003ca href=\"sign_in.php\" title=\"Sign_in\"\u003eSign in\u003c/a\u003e\u0026nbsp;\u003ca href=\"sign_up.php\" title=\"Sign_up\"\u003eSign up!!!\u003c/a\u003e\u003c/p\u003e\r\n\t\t\t\u003c/div\u003e\r\n        \u003c!-- [end] Information bar --\u003e\r\n\t\t\u003cdiv id=\"menuh\"\u003e\r\n            \u003cul\u003e\r\n                \u003cli\u003e\u003ca href=index.php title=\"Home\"\u003eHome\u003c/a\u003e\u003c/li\u003e\r\n                \u003cli\u003e\u003ca href=\"free.php\" title=\"Download\"\u003eDownload\u003c/a\u003e\u003c/li\u003e\r\n                \u003cli\u003e\u003ca href=\"projects.php\" title=\"Projects\"\u003eProjects\u003c/a\u003e\u003c/li\u003e\r\n                \u003cli\u003e\u003ca href=\"#\" title=\"Forum\"\u003eForum\u003c/a\u003e\u003c/li\u003e\r\n                \u003cli\u003e\u003ca href=\"render.php\" title=\"Therendering\"\u003eRendering\u003c/a\u003e\u003c/li\u003e\r\n                \u003cli\u003e\u003ca href=\"contact.php\" title=\"Contact\"\u003eContact us\u003c/a\u003e\u003c/li\u003e\r\n            \u003c/ul\u003e\r\n        \u003c/div\u003e    \u003c/div\u003e\r\n    \u003cdiv id=\"content\"\u003e\r\n    \t\u003cdiv id=\"left\"\u003e\r\n        \t\u003cdiv id=\"left-p\"\u003e\r\n            \t\u003c!-- [begin] Zone of contents --\u003e\r\n                \u003c!-- I can modify the code here --\u003e\r\n                \r\n            \t                \u003ch2\u003eWelcome to DevilFunding\u003c/h2\u003e\r\n            \t\u003cdiv id=\"conteneur\"\u003eDevilFunding is make for all those who want to realize theirs dreams. \u003cstrong\u003eThis site aims to promote crowdfunding in the darkweb.\u003c/strong\u003e\u003c/div\u003e\r\n               \u003cdiv id=\"conteneur\"\u003eRegistration is required in order to continue further.\u003cbr\u003eIf you have crazy projets that you would funding, please to read the notice before contact us.\u003c/div\u003e\r\n              \u003cdiv id=\"conteneur\"\u003eFunders will be the only ones to enjoy the end results.\u003cbr\u003e\r\n\t      In cases of artistic projects (photo, video ...), the financiers will have a copy; according to the will of the author, a copy can either be put on sale on the website or be available to all members of the site.\u003cbr\u003e\r\n\t      For other projects (software or other), the financiers will also be compensated.\u003c/div\u003e\r\n\t      \r\n\t\r\n                \r\n                \u003ch2\u003e\u003c/h2\u003e\r\n              \t\u003cdiv align=\"center\" style=\"padding-left: 5px;\"\u003e\u003cimg src=\"corps/images/Bitcoin.png\" alt=\"\" /\u003e\u003c/div\u003e\r\n                                \u003c!-- [end] Zone of contents --\u003e\r\n            \u003c/div\u003e\r\n        \u003c/div\u003e\r\n        \u003cdiv id=\"right\"\u003e\r\n        \t\u003cdiv id=\"right-p\"\u003e\r\n            \t\u003cdiv class=\"rss\"\u003e\r\n                \t\u003cp\u003eCurrently there are 3 ongoing projects. Why not yours !!!\u003c/p\u003e\r\n                \u003c/div\u003e\r\n\t\t \u003c!-- [begin] Rubrique --\u003e\r\n                \u003ch3\u003eThey trust us\u003c/h3\u003e\r\n\t\t\u003cdiv class=\"rubrique\"\u003e\r\n\t\t\t\u003cdiv class=\"rubrique-top\"\u003e\u003c/div\u003e\r\n\t\t\t\t\t\u003cdiv class=\"rubrique-content\"\u003e\r\n                        \u003cul\u003e\r\n\t\t\t\t\u003cli\u003eHere will share your experience.\u003c/li\u003e\r\n\t\t\t\u003c/ul\u003e\r\n\t\t\t\r\n\t\t \u003c/div\u003e\r\n\t\t\t\t\t\r\n                \t\u003cdiv class=\"rubrique-bottom\"\u003e\u003c/div\u003e\r\n                \u003c/div\u003e\r\n               \r\n                \r\n                \u003c!-- [end] Rubrique --\u003e\r\n            \u003c/div\u003e\r\n        \u003c/div\u003e\r\n    \u003c/div\u003e\r\n\u003c/div\u003e\r\n\u003cdiv class=\"clear\"\u003e\u003c/div\u003e\r\n\u003cdiv id=\"footer\"\u003e\r\n\t\u003c!-- foot--\u003e\r\n\r\n\u003cdiv id=\"footer-inner\"\u003e\r\n        \u003cdiv id=\"footer-left\"\u003e\r\n        \t\u003ch3\u003eCopyright\u003c/h3\u003e\r\n            \u003cp\u003e\u0026copy; 2016 DevilFunding. All rights reserved.\u003c/p\u003e\r\n            \u003cp\u003eLet us act to preserve our freedom.\u003cbr /\u003e\u003ca href=\"index.php\" title=\"DevilFunding\"\u003eDevil seeking beneficent Angel\u003c/a\u003ericosrd@sigaint.org\u003c/p\u003e\r\n            \r\n            \u003cdiv id=\"w3c\"\u003e\r\n\t\t\t\t\u003cul\u003e\r\n                \t\u003cli\u003e\u003ca href=\"#\" title=\"Valide CSS\"\u003eValide CSS\u003c/a\u003e\u003c/li\u003e\r\n                    \u003cli\u003e\u003ca href=\"#\" title=\"Valide XHTML\"\u003eValide XHTML\u003c/a\u003e\u003c/li\u003e\r\n                    \u003cli\u003e\u003ca href=\"#\" title=\"Valide XHTML\"\u003edonation: 1KWv6EvS9xg6ZTJTCa8zYj1XqMiGZ458kg\u003c/a\u003e\u003c/li\u003e\r\n                \u003c/ul\u003e\r\n            \u003c/div\u003e\r\n        \u003c/div\u003e\r\n        \u003cdiv id=\"footer-middle\"\u003e\r\n            \u003ch3\u003ePartners \u0026amp; Links\u003c/h3\u003e\r\n            \u003cul\u003e\r\n            \t\u003cli\u003e\u003ca href=\"https://www.preev.com\" title=\"Price\"\u003eThe price of Bitcoin\u003c/a\u003e\u003c/li\u003e\r\n                \u003cli\u003e\u003ca href=\"https://www.bitboat.net\" title=\"\"\u003eGet Bitcoin\u003c/a\u003e\u003c/li\u003e\r\n                \u003cli\u003e\u003ca href=\"#\" title=\"contact.php\"\u003eBeing Partner\u003c/a\u003e\u003c/li\u003e\r\n                \u003cli\u003e\u003ca href=\"#\" title=\"\"\u003e\u003c/a\u003e\u003c/li\u003e\r\n            \u003c/ul\u003e\r\n        \u003c/div\u003e\r\n        \u003cdiv id=\"footer-right\"\u003e\r\n            \u003ch3\u003eLast news\u003c/h3\u003e\r\n            \u003cul\u003e\r\n            \t\u003cli\u003e\u003ca href=\"#\" title=\"\"\u003e\u003cstrong style=\"color: #94c600; padding-right: 10px;\"\u003e17/02\u003c/strong\u003e\u003c/a\u003eForum coming soon\u003c/li\u003e\r\n                \u003cli\u003e\u003ca href=\"#\" title=\"\"\u003e\u003cstrong style=\"color: #94c600; padding-right: 10px;\"\u003e17/02\u003c/strong\u003e\u003c/a\u003ePurchase new server\u003c/li\u003e\r\n                \u003cli\u003e\u003ca href=\"#\" title=\"\"\u003e\u003cstrong style=\"color: #94c600; padding-right: 10px;\"\u003e18/01\u003c/strong\u003e\u003c/a\u003eLooking for server\u003c/li\u003e\r\n                \u003cli\u003e\u003ca href=\"#\" title=\"\"\u003e\u003cstrong style=\"color: #94c600; padding-right: 10px;\"\u003e17/01\u003c/strong\u003e\u003c/a\u003eCreation of the website\u003c/li\u003e\r\n            \u003c/ul\u003e\r\n        \u003c/div\u003e\r\n    \u003c/div\u003e\r\n\u003c/div\u003e\r\n\r\n\u003c/body\u003e\r\n\r\n\u003c/html\u003e\r\n","pageTitle":"DevilFunding // The crowdfunding of the darkweb","responseHeaders":{"CACHE-CONTROL":"no-store, no-cache, must-revalidate, post-check=0, pre-check=0","CONTENT-TYPE":"text/html; charset=UTF-8","DATE":"Sat, 23 Jul 2016 18:16:54 GMT","EXPIRES":"Thu, 19 Nov 1981 08:52:00 GMT","PRAGMA":"no-cache","SERVER":"Apache","SET-COOKIE":"PHPSESSID=0pvf4gpensum24d59skm2hbin616q6sh; path=/; HttpOnly","VARY":"Accept-Encoding","X-CONTENT-TYPE-OPTIONS":"nosniff","X-FRAME-OPTIONS":"sameorigin","X-XSS-PROTECTION":"1; mode=block"},"bitcoinAddresses":null,"sshKey":"81:cb:d2:d4:f7:e4:8c:6b:1a:92:07:42:cd:e2:42:23","ftpFingerprint":"","ftpBanner":"","smtpFingerprint":"","smtpBanner":""}
